LICENSE
MANIFEST.in
README.rst
setup.py
iucm/__init__.py
iucm/_dist.c
iucm/dist.py
iucm/energy_consumption.py
iucm/main.py
iucm/model.py
iucm/utils.py
iucm/version.py
iucm.egg-info/PKG-INFO
iucm.egg-info/SOURCES.txt
iucm.egg-info/dependency_links.txt
iucm.egg-info/entry_points.txt
iucm.egg-info/not-zip-safe
iucm.egg-info/requires.txt
iucm.egg-info/top_level.txt