Metadata-Version: 1.1
Name: iucm
Version: 0.2.0
Summary: Integrated Urban Complexity Model
Home-page: https://github.com/Chilipp/iucm
Author: Philipp Sommer and Roger Cremades
Author-email: philipp.sommer@unil.ch
License: UNKNOWN
Keywords: urban-planning climate energy python modeling
Platform: UNKNOWN
Classifier: Development Status :: 5 - Production/Stable
Classifier: Intended Audience :: Developers
Classifier: Topic :: Scientific/Engineering
Classifier: License :: OSI Approved :: GNU General Public License v3 or later (GPLv3+)
Classifier: Programming Language :: Python :: 2
Classifier: Programming Language :: Python :: 2.7
Classifier: Programming Language :: Python :: 3
Classifier: Programming Language :: Python :: 3.4
Classifier: Programming Language :: Python :: 3.5
Classifier: Operating System :: OS Independent
